qfunc/__init__.py
qfunc/decoher.py
qfunc-0.3.0.dist-info/licenses/LICENSE
qfunc-0.3.0.dist-info/METADATA
qfunc-0.3.0.dist-info/WHEEL
qfunc-0.3.0.dist-info/top_level.txt
qfunc-0.3.0.dist-info/RECORD
